jupyterlab_unicore_shell/__init__.py
jupyterlab_unicore_shell/_version.py
jupyterlab_unicore_shell/handlers.py
jupyterlab_unicore_shell-0.4.5.data/data/etc/jupyter/jupyter_server_config.d/jupyterlab_unicore_shell.json
jupyterlab_unicore_shell-0.4.5.data/data/share/jupyter/labextensions/jupyterlab-unicore-shell/package.json
jupyterlab_unicore_shell-0.4.5.data/data/share/jupyter/labextensions/jupyterlab-unicore-shell/static/259.ec34f1f403ac94ab77db.js
jupyterlab_unicore_shell-0.4.5.data/data/share/jupyter/labextensions/jupyterlab-unicore-shell/static/259.ec34f1f403ac94ab77db.js.LICENSE.txt
jupyterlab_unicore_shell-0.4.5.data/data/share/jupyter/labextensions/jupyterlab-unicore-shell/static/375.5e8e420cceb8754049d0.js
jupyterlab_unicore_shell-0.4.5.data/data/share/jupyter/labextensions/jupyterlab-unicore-shell/static/375.5e8e420cceb8754049d0.js.LICENSE.txt
jupyterlab_unicore_shell-0.4.5.data/data/share/jupyter/labextensions/jupyterlab-unicore-shell/static/395.b9d49a0ea1872c904f98.js
jupyterlab_unicore_shell-0.4.5.data/data/share/jupyter/labextensions/jupyterlab-unicore-shell/static/395.b9d49a0ea1872c904f98.js.LICENSE.txt
jupyterlab_unicore_shell-0.4.5.data/data/share/jupyter/labextensions/jupyterlab-unicore-shell/static/459.93961eab22ba989f8c49.js
jupyterlab_unicore_shell-0.4.5.data/data/share/jupyter/labextensions/jupyterlab-unicore-shell/static/459.93961eab22ba989f8c49.js.LICENSE.txt
jupyterlab_unicore_shell-0.4.5.data/data/share/jupyter/labextensions/jupyterlab-unicore-shell/static/728.e2e2240eabaa931b3ec4.js
jupyterlab_unicore_shell-0.4.5.data/data/share/jupyter/labextensions/jupyterlab-unicore-shell/static/880.74c678290a6598d14425.js
jupyterlab_unicore_shell-0.4.5.data/data/share/jupyter/labextensions/jupyterlab-unicore-shell/static/92.6150dc25294e98eb4cbe.js
jupyterlab_unicore_shell-0.4.5.data/data/share/jupyter/labextensions/jupyterlab-unicore-shell/static/remoteEntry.f977d7f139eb9b32f7c4.js
jupyterlab_unicore_shell-0.4.5.dist-info/METADATA
jupyterlab_unicore_shell-0.4.5.dist-info/WHEEL
jupyterlab_unicore_shell-0.4.5.dist-info/licenses/LICENSE
jupyterlab_unicore_shell-0.4.5.dist-info/RECORD
