Metadata-Version: 2.4
Name: jupyterlab_unicore_shell
Version: 0.4.5
Dynamic: Author
Dynamic: Author-email
Summary: A JupyterLab extension to run Remote Terminals via UNICORE.
Project-URL: Homepage, https://github.com/jsc-jupyter/jupyterlab-unicore-shell
Project-URL: Bug Tracker, https://github.com/jsc-jupyter/jupyterlab-unicore-shell/issues
Project-URL: Repository, https://github.com/jsc-jupyter/jupyterlab-unicore-shell.git
License: BSD 3-Clause License
License-File: LICENSE
Keywords: jupyter,jupyterlab,jupyterlab-extension
Classifier: Framework :: Jupyter
Classifier: Framework :: Jupyter :: JupyterLab
Classifier: Framework :: Jupyter :: JupyterLab :: 4
Classifier: Framework :: Jupyter :: JupyterLab :: Extensions
Classifier: Framework :: Jupyter :: JupyterLab :: Extensions :: Prebuilt
Classifier: License :: OSI Approved :: BSD License
Classifier: Programming Language :: Python
Classifier: Programming Language :: Python :: 3
Classifier: Programming Language :: Python :: 3.9
Classifier: Programming Language :: Python :: 3.10
Classifier: Programming Language :: Python :: 3.11
Classifier: Programming Language :: Python :: 3.12
Classifier: Programming Language :: Python :: 3.13
Requires-Python: >=3.9
Requires-Dist: jupyter-server<3,>=2.4.0
Requires-Dist: pyunicore>=1.3.5
